windseeker/__init__.py
windseeker/cli.py
windseeker/main.py
windseeker-1.1.3.dist-info/licenses/LICENSE
windseeker-1.1.3.dist-info/METADATA
windseeker-1.1.3.dist-info/WHEEL
windseeker-1.1.3.dist-info/entry_points.txt
windseeker-1.1.3.dist-info/top_level.txt
windseeker-1.1.3.dist-info/RECORD
