Metadata-Version: 2.4
Name: windseeker
Version: 1.1.3
Summary: SysML v2 dependency analysis, notebook generation, execution, and view extraction tool
Author: Windseeker Contributors
License: MIT
Requires-Python: >=3.10
License-File: LICENSE
Requires-Dist: networkx>=3.2
Requires-Dist: matplotlib>=3.8
Requires-Dist: nbformat>=5.9
Requires-Dist: nbclient>=0.9
Requires-Dist: jupyter>=1.0
Requires-Dist: cairosvg>=2.7
Requires-Dist: pillow>=10.0
Requires-Dist: typer>=0.12
Requires-Dist: rich>=13.7
Requires-Dist: lxml>=5.0
Provides-Extra: dev
Requires-Dist: ruff>=0.6; extra == "dev"
Requires-Dist: pytest>=8; extra == "dev"
Requires-Dist: python-semantic-release>=10.0.0; extra == "dev"
Requires-Dist: pre-commit>=3.7; extra == "dev"
Dynamic: license-file
